SpectroBinary/__init__.py
SpectroBinary/doppler_shift.py
SpectroBinary/test_doppler_shift.py
SpectroBinary/trajectory.py
SpectroBinary-1.0.0.dist-info/LICENSE
SpectroBinary-1.0.0.dist-info/METADATA
SpectroBinary-1.0.0.dist-info/WHEEL
SpectroBinary-1.0.0.dist-info/top_level.txt
SpectroBinary-1.0.0.dist-info/RECORD
