Metadata-Version: 2.1
Name: SpectroBinary
Version: 1.0.0
Summary: UNKNOWN
Home-page: https://github.com/MASTERAMARJEET/code-astro-2021
Author: Amarjeet Kumar, Bhuvanambiga Pari
Author-email: masteramarjeetkumar@gmail.com
License: MIT
Platform: UNKNOWN
Requires-Dist: numpy
Requires-Dist: matplotlib
